mlessence/__init__.py
mlessence-0.0.0.1.dist-info/LICENSE
mlessence-0.0.0.1.dist-info/METADATA
mlessence-0.0.0.1.dist-info/WHEEL
mlessence-0.0.0.1.dist-info/top_level.txt
mlessence-0.0.0.1.dist-info/RECORD
